{
    "author": "I_love_beer_2021",
    "created_utc": 1627495020.0,
    "distinguished": null,
    "edited": false,
    "id": "otf8mc",
    "text_only": false,
    "flair_text": "Opinion \ud83d\udc7d",
    "name": "t3_otf8mc",
    "num_comments": 60,
    "permalink": "/r/Superstonk/comments/otf8mc/volume_up_over_300_8_to_1_buy_ratio_and_price/",
    "score": 2030,
    "selftext": "",
    "title": "Volume up over 300%, 8 to 1 buy ratio and price drop 6%.. they are desperately trying to scare away new investors",
    "upvote_ratio": 0.98,
    "url": "https://i.redd.it/wbdg427rszd71.jpg"
}