{
    "author": "ChiefCokkahoe",
    "created_utc": 1619896142.0,
    "distinguished": null,
    "edited": false,
    "id": "n2p23x",
    "text_only": false,
    "flair_text": "Fluff \u2601",
    "name": "t3_n2p23x",
    "num_comments": 241,
    "permalink": "/r/Superstonk/comments/n2p23x/i_cant_wait_for_the_moass_to_be_over_so_we_can/",
    "score": 9175,
    "selftext": "",
    "title": "I can\u2019t wait for the MOASS to be over so we can all hang out with Keith on livestream for an evening, I miss him \ud83d\ude2d",
    "upvote_ratio": 0.97,
    "url": "https://i.redd.it/ptii4z3e5kw61.jpg"
}