{
    "author": "Dwellerofthecrags",
    "created_utc": 1621378823.0,
    "distinguished": null,
    "edited": false,
    "id": "nfozxl",
    "text_only": false,
    "flair_text": "News \ud83d\udcf0 | Media \ud83d\udcf1",
    "name": "t3_nfozxl",
    "num_comments": 61,
    "permalink": "/r/Superstonk/comments/nfozxl/ama_with_wes_christian_hosted_by_dave_lauer_and/",
    "score": 2824,
    "selftext": "",
    "title": "AMA with Wes Christian hosted by Dave Lauer and jsmar18 was excellent and contained so much confirmation about the state of market manipulation in general that we all have seen with GME. 296k here, 13.9k watched, 4.5k upvoted. YOU KNOW WHAT TO DO!",
    "upvote_ratio": 0.98,
    "url": "https://i.redd.it/u42sldwmlyz61.jpg"
}