{
    "author": "Dwellerofthecrags",
    "created_utc": 1620790634.0,
    "distinguished": null,
    "edited": false,
    "id": "nafjek",
    "text_only": false,
    "flair_text": "HODL \ud83d\udc8e\ud83d\ude4c",
    "name": "t3_nafjek",
    "num_comments": 32,
    "permalink": "/r/Superstonk/comments/nafjek/gamestop_twitter_account_today_dfv_quadrupling/",
    "score": 517,
    "selftext": "",
    "title": "GameStop twitter account today, DFV quadrupling down, RC leading the company transformation, Warden's triangle ladder, the return of Rensole, the simple facts depicted in 1 zoomed out image (for perspective), and 1 t-shirt to sum it all up! \ud83d\udc8e\u270b",
    "upvote_ratio": 0.96,
    "url": "https://www.reddit.com/gallery/nafjek"
}