{
    "author": "BlitzFritzXX",
    "created_utc": 1626351948.0,
    "distinguished": null,
    "edited": false,
    "id": "okrs5i",
    "text_only": false,
    "flair_text": "HODL \ud83d\udc8e\ud83d\ude4c",
    "name": "t3_okrs5i",
    "num_comments": 65,
    "permalink": "/r/Superstonk/comments/okrs5i/a_record_of_whopping_435000_put_options_and/",
    "score": 1598,
    "selftext": "",
    "title": "A record of whopping 435.000 put options and 127.000 call options are due to expire tomorrow out of the money and the price has been aggressively driven down over the last 2 weeks on no volume. Simple ape:\u201dFcking obvious blatant manipulation again in broad daylight\u201d\ud83e\udd2c\ud83d\udca5\u26a1\ufe0f\u26a1\ufe0f\ud83c\udf08\ud83d\udc3b",
    "upvote_ratio": 0.97,
    "url": "https://i.redd.it/wvtothftddb71.jpg"
}