{
    "author": "jacoby40",
    "created_utc": 1622738415.0,
    "distinguished": null,
    "edited": false,
    "id": "nrhtqy",
    "text_only": false,
    "flair_text": "HODL \ud83d\udc8e\ud83d\ude4c",
    "name": "t3_nrhtqy",
    "num_comments": 559,
    "permalink": "/r/Superstonk/comments/nrhtqy/ryan_cohen_on_twitter/",
    "score": 6624,
    "selftext": "",
    "title": "Ryan Cohen on Twitter",
    "upvote_ratio": 0.98,
    "url": "https://twitter.com/ryancohen/status/1400492465442811904?s=21"
}