{
    "author": "Stingerdraws",
    "created_utc": 1627904231.0,
    "distinguished": null,
    "edited": false,
    "id": "owco0b",
    "text_only": false,
    "flair_text": "Meme \ud83e\udd23",
    "name": "t3_owco0b",
    "num_comments": 16,
    "permalink": "/r/Superstonk/comments/owco0b/msm_when_they_see_that_reddit_users_have_found/",
    "score": 662,
    "selftext": "",
    "title": "MSM when they see that Reddit users have found potentially multiple international economic bubbles that are about to burst.",
    "upvote_ratio": 0.95,
    "url": "https://i.redd.it/m2zr35zhlxe71.gif"
}