{
    "author": "InvisibleLeftHand",
    "created_utc": 1619206319.0,
    "distinguished": null,
    "edited": false,
    "id": "mx365t",
    "text_only": false,
    "flair_text": null,
    "name": "t3_mx365t",
    "num_comments": 9,
    "permalink": "/r/GME/comments/mx365t/do_not_paper_hand_margin_calls_can_take_up_to_5/",
    "score": 620,
    "selftext": "",
    "title": "Do NOT paper hand. Margin calls can take up to 5 days. Reposting this because shitadel interns are downvoting it to hell",
    "upvote_ratio": 0.97,
    "url": "https://i.redd.it/9zf57u089yu61.jpg"
}