{
    "author": "sdilley14",
    "created_utc": 1624413201.0,
    "distinguished": null,
    "edited": false,
    "id": "o62wzw",
    "text_only": false,
    "flair_text": "Fluff \u2601",
    "name": "t3_o62wzw",
    "num_comments": 495,
    "permalink": "/r/Superstonk/comments/o62wzw/ken_griffin_shitadel_what_a_guy_pos_he_is_where/",
    "score": 4239,
    "selftext": "",
    "title": "\u201cKen Griffin - Shitadel. What a guy (POS) HE is. Where the hell is Ken? He\u2019s trying to hide some of his money. Look, he doesn\u2019t want to stand up. Where the hell is Ken??\u201d \ud83d\ude02",
    "upvote_ratio": 0.92,
    "url": "https://v.redd.it/us5ryj1x8x671"
}