{
    "author": "twittafingahsma",
    "created_utc": 1624565493.0,
    "distinguished": null,
    "edited": false,
    "id": "o78z84",
    "text_only": false,
    "flair_text": "\ud835\uddd7\ud835\uddee\ud835\ude01\ud835\uddee",
    "name": "t3_o78z84",
    "num_comments": 47,
    "permalink": "/r/DDintoGME/comments/o78z84/fidelity_top_orders_by_customers_update_thursday/",
    "score": 806,
    "selftext": "",
    "title": "Fidelity Top Orders by Customers Update - Thursday June 24, 2021. Buys 76% & Sells 24%. Stonk is down $7.03 (-3.21%) on 3.8m volume. Buy orders have not been below 70% for 9 straight trading days! Orders \u2260 share volume, this data helps display retail sentiment.",
    "upvote_ratio": 0.97,
    "url": "https://i.redd.it/08g6fi7ft9771.png"
}