{
    "author": "Yonsei",
    "created_utc": 1616740136.0,
    "distinguished": null,
    "edited": false,
    "id": "mdid9l",
    "text_only": false,
    "flair_text": "Discussion",
    "name": "t3_mdid9l",
    "num_comments": 34,
    "permalink": "/r/GME/comments/mdid9l/gamestop_is_selling_a_rocket_cats_tshirt_ryan_is/",
    "score": 826,
    "selftext": "",
    "title": "GameStop is selling a Rocket Cats \ud83d\ude80 T-Shirt?! Ryan is definitely memeing on us.\ud83d\udc8e\ud83d\ude4c\ud83d\ude80",
    "upvote_ratio": 0.99,
    "url": "https://i.redd.it/yrmcbcuygbp61.jpg"
}