{
    "author": "Wallstreet_Owes_Me",
    "created_utc": 1627961981.0,
    "distinguished": null,
    "edited": false,
    "id": "owv3gw",
    "text_only": false,
    "flair_text": "Education \ud83d\udc68\u200d\ud83c\udfeb | Data \ud83d\udd22",
    "name": "t3_owv3gw",
    "num_comments": 14,
    "permalink": "/r/Superstonk/comments/owv3gw/no_one_wants_to_see_the_market_crashbut_thats/",
    "score": 504,
    "selftext": "",
    "title": "No one wants to see the market crash..but that\u2019s exactly where we are headed. The triggers are already there!",
    "upvote_ratio": 0.97,
    "url": "https://i.redd.it/vhdmtts9d2f71.jpg"
}