{
    "author": "Alieniity",
    "created_utc": 1622860632.0,
    "distinguished": null,
    "edited": false,
    "id": "nslr6p",
    "text_only": false,
    "flair_id": "a48b5c8e-8ff4-11eb-89b6-0e67f4f5fcb3",
    "flair_text": "News \ud83d\udcf0 | Media \ud83d\udcf1",
    "name": "t3_nslr6p",
    "num_comments": 644,
    "permalink": "/r/Superstonk/comments/nslr6p/appreciate_it_cnbc_without_you_i_never_would_have/",
    "score": 14339,
    "selftext": "",
    "title": "Appreciate it, CNBC! Without you, I never would have known about the naked short selling! \ud83d\ude80\ud83d\ude80\ud83d\ude80",
    "upvote_ratio": 0.97,
    "url": "https://i.redd.it/6e9ofvz40d371.jpg"
}