{
    "author": "canispeaktoyourmangr",
    "created_utc": 1627330720.0,
    "distinguished": null,
    "edited": false,
    "id": "os74c7",
    "text_only": false,
    "flair_text": "HODL \ud83d\udc8e\ud83d\ude4c",
    "name": "t3_os74c7",
    "num_comments": 84,
    "permalink": "/r/Superstonk/comments/os74c7/volume_low_score_drier_than_my_bank_account/",
    "score": 6306,
    "selftext": "",
    "title": "\u26aa\ufe0f VOLUME LOW SCORE \u26aa\ufe0f Drier than my bank account",
    "upvote_ratio": 0.99,
    "url": "https://i.redd.it/5b38wfo78md71.jpg"
}