{
    "author": "GildDigger",
    "created_utc": 1625033472.0,
    "distinguished": null,
    "edited": false,
    "id": "oar38h",
    "text_only": false,
    "flair_id": "57abfac2-85f9-11eb-a149-0e1c812e54f7",
    "flair_text": "Discussion \ud83e\udd8d",
    "name": "t3_oar38h",
    "num_comments": 85,
    "permalink": "/r/Superstonk/comments/oar38h/havent_seen_very_much_talk_about_tomorrow_being/",
    "score": 1202,
    "selftext": "",
    "title": "Haven\u2019t seen very much talk about tomorrow being the end of Q2. Did u/Criand not jack anything else\u2019s tits for this??? \ud83d\ude80\ud83d\ude80\ud83d\ude80\ud83d\udea8\ud83d\udea8\ud83d\udea8\ud83c\udf15\ud83c\udf15\ud83c\udf15",
    "upvote_ratio": 0.93,
    "url": "https://i.redd.it/hjn1kf8bhc871.jpg"
}