{
    "author": "akgogreen",
    "created_utc": 1626712757.0,
    "distinguished": null,
    "edited": false,
    "id": "onhrit",
    "text_only": false,
    "flair_text": "Meme \ud83e\udd23",
    "name": "t3_onhrit",
    "num_comments": 870,
    "permalink": "/r/Superstonk/comments/onhrit/what_happened_to_this_mentality_people_are_very/",
    "score": 15395,
    "selftext": "",
    "title": "What happened to this mentality? People are very quick to state lately how little they care about their fellow ape. But wasn't that the default mindset? We didn't care who each other was personally, we just cared that we are all in this together. I want to go back to these mindsets, not the flipside",
    "upvote_ratio": 0.91,
    "url": "https://i.redd.it/d91qshso67c71.jpg"
}