{
    "author": "-hando",
    "created_utc": 1624752099.0,
    "distinguished": null,
    "edited": false,
    "id": "o8m37r",
    "text_only": true,
    "flair_id": "57abfac2-85f9-11eb-a149-0e1c812e54f7",
    "flair_text": "Discussion \ud83e\udd8d",
    "name": "t3_o8m37r",
    "num_comments": 95,
    "permalink": "/r/Superstonk/comments/o8m37r/im_fucking_jacked_about_gamestop_selling_board/",
    "score": 853,
    "selftext": "Dungeons and Dragons is one of the OG games, a marvelous way to explore our own creativity and personalities, it made a big difference in my household over multiple generations.\n\nI would love to see my favorite store on the Citadel (GameStop) stocked to the tits with the full range of D&D books for players and DMs, high quality dice, and minis (WE DROP MORTGAGES ON THESE)\n\nARE YOU YOU GUYS PICKING UP WHAT IM PUTTING DOWN?\n\nI LIKE TO SLAY DRAGONS WITH MY **DIAMOND** HANDS AND SLAM ELF PUSS.",
    "title": "I'm fucking JACKED about GameStop selling Board Games, but how about some love for D&D?",
    "upvote_ratio": 0.96,
    "url": "https://www.reddit.com/r/Superstonk/comments/o8m37r/im_fucking_jacked_about_gamestop_selling_board/"
}