{
    "author": "bboarder864",
    "created_utc": 1624379820.0,
    "distinguished": null,
    "edited": false,
    "id": "o5rb3m",
    "text_only": false,
    "flair_text": "Opinion \ud83d\udc7d",
    "name": "t3_o5rb3m",
    "num_comments": 269,
    "permalink": "/r/Superstonk/comments/o5rb3m/psa_can_we_please_stop_with_these_low_effort/",
    "score": 3997,
    "selftext": "",
    "title": "PSA: Can we PLEASE stop with these low effort Kenny pictures. A quick Google search and there's an endless supply for shills to forum slide. Ape out. \u270c\ufe0f\ud83d\ude80\ud83c\udf4c",
    "upvote_ratio": 0.86,
    "url": "https://i.redd.it/wppvpv2ohu671.jpg"
}