{
    "author": "ConradT16",
    "created_utc": 1621953461.0,
    "distinguished": null,
    "edited": false,
    "id": "nkr95d",
    "text_only": false,
    "flair_text": "\ud83d\ude02 Memes \ud83d\ude39",
    "name": "t3_nkr95d",
    "num_comments": 26,
    "permalink": "/r/GME/comments/nkr95d/t35_failed_to_deliver_but_ol_reliable_t21_is/",
    "score": 764,
    "selftext": "",
    "title": "T+35 Failed to Deliver but ol\u2019 reliable T+21 is coming in clutch",
    "upvote_ratio": 0.98,
    "url": "https://i.redd.it/wrkghdyu2a171.jpg"
}