{
    "author": "cactus-hugger",
    "created_utc": 1618855120.0,
    "distinguished": null,
    "edited": false,
    "id": "mu6ewj",
    "text_only": false,
    "flair_text": "Opinion \ud83d\udc7d",
    "name": "t3_mu6ewj",
    "num_comments": 961,
    "permalink": "/r/Superstonk/comments/mu6ewj/proposal_to_change_lambo_to_roadster_lamborghinis/",
    "score": 5531,
    "selftext": "",
    "title": "Proposal to change Lambo to Roadster. Lamborghinis are boomer cars.",
    "upvote_ratio": 0.93,
    "url": "https://i.redd.it/7h9fdjvv56u61.png"
}