{
    "author": "Constant_Lack3821",
    "created_utc": 1616136195.0,
    "distinguished": null,
    "edited": false,
    "id": "m8b96m",
    "text_only": true,
    "flair_text": "Fluff",
    "name": "t3_m8b96m",
    "num_comments": 178,
    "permalink": "/r/GME/comments/m8b96m/can_i_get_a_show_of_hands_for_all_the_europeans/",
    "score": 1050,
    "selftext": "Holding to 1mil. I am gonna start as many companies as I can manage and help as many people I can who lost their jobs due to corona.",
    "title": "Can I get a show of hands for all the Europeans still diamond handing\ud83d\udc8e\ud83d\udc8e\ud83d\udc8e\ud83d\udd90",
    "upvote_ratio": 0.97,
    "url": "https://www.reddit.com/r/GME/comments/m8b96m/can_i_get_a_show_of_hands_for_all_the_europeans/"
}