{
    "author": "jacksparrow2905",
    "created_utc": 1623665267.0,
    "distinguished": null,
    "edited": false,
    "id": "nzjg8g",
    "text_only": false,
    "flair_id": "a44bae56-6ee6-11eb-9f7e-0e185bbf0ec3",
    "flair_text": "\ud83d\ude02 Memes \ud83d\ude39",
    "name": "t3_nzjg8g",
    "num_comments": 179,
    "permalink": "/r/GME/comments/nzjg8g/new_apes_be_like/",
    "score": 3867,
    "selftext": "",
    "title": "New apes be like...",
    "upvote_ratio": 0.96,
    "url": "https://i.redd.it/ve4q0zrxg7571.jpg"
}