{
    "author": "BakaSandwich",
    "created_utc": 1616780999.0,
    "distinguished": null,
    "edited": 1616783499.0,
    "id": "mdu8dx",
    "text_only": true,
    "flair_id": "eb291992-7082-11eb-b396-0e981632a78d",
    "flair_text": "Shitpost",
    "name": "t3_mdu8dx",
    "num_comments": 50,
    "permalink": "/r/GME/comments/mdu8dx/ken_griffins_broke_tips_you_can_keep_a_perputal/",
    "score": 687,
    "selftext": "This technique was passed down from generation to generation, first practiced by the Listerine Quants of 2008, it has since made its way to the Hedgetown martial arts scene with student Gabe Plotkin of Melvin's Mouthwash dojo bringing it to new heights of shorting the mouthwash.\n\n\nWhat are some other poor man's tips for our fellow hedgethusiasts?\n\n**Edit:** *whoops, just noticed the typo in the last title sentence. Too many crayola smoothies...*",
    "title": "Ken Griffin's Broke Tips: You can keep a perputal bottle of mouthwash going by backwashing. Doing this techniques allows you to short the mouthwash by 900%",
    "upvote_ratio": 0.98,
    "url": "https://www.reddit.com/r/GME/comments/mdu8dx/ken_griffins_broke_tips_you_can_keep_a_perputal/"
}