{
    "author": "PianistIntelligent75",
    "created_utc": 1625667640.0,
    "distinguished": null,
    "edited": false,
    "id": "ofjuf8",
    "text_only": true,
    "flair_text": "Opinion \ud83d\udc7d",
    "name": "t3_ofjuf8",
    "num_comments": 88,
    "permalink": "/r/Superstonk/comments/ofjuf8/if_they_dropped_it_by_10_in_half_an_hour_and_with/",
    "score": 1968,
    "selftext": "If they dropped it by 10% in half an hour and with 1 million volume, to me there is only explanation: THEY ARE DESPERATE.\n\nHODL AND BUY till mother fukers go bankrupt! \ud83d\udc8e \u270b\n\nLove you apes!\n\nCharacters to fill 250 Characters....Characters to fill 250 Characters....Characters to fill 250 Characters....Characters to fill 250 Characters....Characters to fill 250 Characters....Characters to fill 250 Characters....Characters to fill 250 Characters....Characters to fill 250 Characters....Characters to fill 250 Characters....Characters to fill 250 Characters....Characters to fill 250 Characters....Characters to fill 250 Characters....Characters to fill 250 Characters....Characters to fill 250 Characters....Characters to fill 250 Characters....Characters to fill 250 Characters....Characters to fill 250 Characters....Characters to fill 250 Characters....",
    "title": "If they dropped it by 10% in half an hour and with 1 million volume, to me there is only explanation: THEY ARE DESPERATE.",
    "upvote_ratio": 0.92,
    "url": "https://www.reddit.com/r/Superstonk/comments/ofjuf8/if_they_dropped_it_by_10_in_half_an_hour_and_with/"
}