{
    "author": "WhaTheFuckus",
    "created_utc": 1624022464.0,
    "distinguished": null,
    "edited": false,
    "id": "o2oyfz",
    "text_only": false,
    "flair_id": "24b09e66-85f9-11eb-b58c-0eb9c97053c1",
    "flair_text": "Meme \ud83e\udd23",
    "name": "t3_o2oyfz",
    "num_comments": 43,
    "permalink": "/r/Superstonk/comments/o2oyfz/tits_jacked_after_hearing_hfs_use_ai_pro_predict/",
    "score": 1833,
    "selftext": "",
    "title": "Tits jacked after hearing HFs use AI pro predict human behavior in the market. You CAN'T predict retarded. Bullish AF.",
    "upvote_ratio": 0.94,
    "url": "https://i.redd.it/2d2m659sy0671.png"
}