{
    "author": "drrdoo",
    "created_utc": 1622458448.0,
    "distinguished": null,
    "edited": false,
    "id": "np0n6h",
    "text_only": false,
    "flair_id": "a48b5c8e-8ff4-11eb-89b6-0e67f4f5fcb3",
    "flair_text": "News \ud83d\udcf0 | Media \ud83d\udcf1",
    "name": "t3_np0n6h",
    "num_comments": 188,
    "permalink": "/r/Superstonk/comments/np0n6h/etoro_wipes_the_floor_with_weekend_fud/",
    "score": 2835,
    "selftext": "",
    "title": "eToro wipes the floor with weekend FUD",
    "upvote_ratio": 0.96,
    "url": "https://i.redd.it/zw621o0gsf271.jpg"
}