{
    "author": "bruiserb1172",
    "created_utc": 1612533532.0,
    "distinguished": null,
    "edited": false,
    "id": "ld7nl7",
    "text_only": true,
    "flair_text": null,
    "name": "t3_ld7nl7",
    "num_comments": 984,
    "permalink": "/r/GME/comments/ld7nl7/price_is_down_hype_is_down_restrictions_are_down/",
    "score": 8382,
    "selftext": "",
    "title": "Price is down. Hype is down. Restrictions are down. Paper hands & doubters have left. If you\u2019re still here - you still believe. Like Mark Cuban said, now we find out what the true power of our online communities are. Now is when we show strength. Not when things are good. Now. \ud83d\udc8e\ud83d\ude80\ud83d\ude4c\ud83d\udc8e\ud83d\ude80",
    "upvote_ratio": 0.93,
    "url": "https://www.reddit.com/r/GME/comments/ld7nl7/price_is_down_hype_is_down_restrictions_are_down/"
}