{
    "author": "ElonMuskTsla",
    "created_utc": 1622229712.0,
    "distinguished": null,
    "edited": false,
    "id": "nn5f3a",
    "text_only": false,
    "flair_text": "HODL \ud83d\udc8e\ud83d\ude4c",
    "name": "t3_nn5f3a",
    "num_comments": 234,
    "permalink": "/r/Superstonk/comments/nn5f3a/shoutout_to_whoever_is_flying_the_plane_over/",
    "score": 8952,
    "selftext": "",
    "title": "Shoutout to whoever is flying the plane over Pompano Beach! \ud83d\udc8e \ud83d\ude4c\ud83c\udffc $GME",
    "upvote_ratio": 0.99,
    "url": "https://v.redd.it/t71mslk7ww171"
}