{
    "author": "Chance_Row_1127",
    "created_utc": 1625860259.0,
    "distinguished": null,
    "edited": false,
    "id": "oh388n",
    "text_only": false,
    "flair_text": "Social Media \ud83d\udcf2\ud83e\udd9c",
    "name": "t3_oh388n",
    "num_comments": 407,
    "permalink": "/r/Superstonk/comments/oh388n/we_are_apes_not_teenagers_but_agree_lol/",
    "score": 8162,
    "selftext": "",
    "title": "We are apes not teenagers but agree lol",
    "upvote_ratio": 0.94,
    "url": "https://i.redd.it/c187zfvrr8a71.jpg"
}