{
    "author": "Thorough_Good_Man",
    "created_utc": 1622944568.0,
    "distinguished": null,
    "edited": false,
    "id": "ntaxs5",
    "text_only": false,
    "flair_id": "681d08c4-85f9-11eb-a69c-0ecac3178a19",
    "flair_text": "Question \u2753",
    "name": "t3_ntaxs5",
    "num_comments": 665,
    "permalink": "/r/Superstonk/comments/ntaxs5/gamestop_stores_are_preparing_to_have_double_the/",
    "score": 8264,
    "selftext": "",
    "title": "GameStop stores are preparing to have double the staff at open on 6/15 & 6/16 for a \u201cSpecial Event\u201d - Found this on the GS employees sub and found it interesting enough to share. Could it be a Nintendo Switch Pro Model launch? Any ideas on what would require twice the staffing at open for two days?",
    "upvote_ratio": 0.97,
    "url": "https://i.redd.it/9o1yadoqxj371.jpg"
}