{
    "author": "PleasecanIcomeBack",
    "created_utc": 1624998558.0,
    "distinguished": null,
    "edited": 1625003052.0,
    "id": "oagl91",
    "text_only": true,
    "flair_text": "Discussion \ud83e\udd8d",
    "name": "t3_oagl91",
    "num_comments": 171,
    "permalink": "/r/Superstonk/comments/oagl91/bedpost_memes_are_trying_to_keep_the_focus_on/",
    "score": 4285,
    "selftext": "Recently there were an influx of great posts highlighting all of the financial terrorists involved in this calamity. \n\n\n[Jeff Yass of Susquehanna](https://en.m.wikipedia.org/wiki/Jeff_Yass?wprov=sfti1)\n\n[Steve Cohen of Point 72](https://en.wikipedia.org/wiki/Steve_Cohen_(businessman)?wprov=sfti1)\n\n[Michael C. Bodson of the DTCC](https://www.crunchbase.com/person/michael-c-bodson)\n\n\nToday, there\u2019s been some forum sliding going on. All of those posts are gone and have been replaced by memable stories about their favourite scapegoat, [Ken Griffin of Citadel](https://en.wikipedia.org/wiki/Kenneth_C%2E_Griffin?wprov=sfti1)\n\n\nIf anyone truly wants to dismantle the corruption in our financial systems, they need to keep their focus on all of the the financial terrorists who orchestrated it. Don\u2019t get distracted.\n\n\n[How Trader Jeff Yass Parlayed Poker and Horse Race Handicapping into a $12 Billion Dollar Fortune](https://www.reddit.com/r/Superstonk/comments/mls4pb/how_trader_jeff_yass_parlayed_poker_and_horse/?utm_source=share&amp;amp;amp;amp;utm_medium=ios_app)\n\n[Overstock CEO Patrick Byrne Names Steve Cohen and Mike Milkin as \u201cSith Lords\u201d ](https://www.reddit.com/r/Superstonk/comments/o8z5to/overstock_ceo_patrick_byrne_names_steve_cohen_and/?utm_source=share&amp;amp;amp;utm_medium=ios_app)\n\n[Introducing Michael Bodson, President and CEO of the DTCC](https://www.reddit.com/r/Superstonk/comments/n1p4o4/introducing_michael_bodson_president_and_ceo_of/?utm_source=share&amp;amp;utm_medium=ios_app)\n\n[A DD Into Steve Cohen, One of the Main Villiains in the GME Saga](https://www.reddit.com/r/Superstonk/comments/nb0261/a_dd_into_steven_a_cohen_one_of_the_main_villains/?utm_source=share&utm_medium=ios_app)\n\nThanks to u/the-eagle-flies, u/Jackbauer13579, u/Stonksgouppp, u/International_Gold20, and others.",
    "title": "Bedpost memes are trying to keep the focus on scapegoat Ken Griffin of Citadel instead of Steve Cohen of Point 72, Jeff Yass of Susquehanna, and the Michael C. Bodson of the DTCC",
    "upvote_ratio": 0.92,
    "url": "https://www.reddit.com/r/Superstonk/comments/oagl91/bedpost_memes_are_trying_to_keep_the_focus_on/"
}