{
    "author": "GinoF2020",
    "created_utc": 1618316366.0,
    "distinguished": null,
    "edited": 1618329983.0,
    "id": "mq12yj",
    "text_only": true,
    "flair_text": "Shitpost",
    "name": "t3_mq12yj",
    "num_comments": 14,
    "permalink": "/r/GME/comments/mq12yj/why_is_msm_so_concerned_about_my_money_and_keeps/",
    "score": 512,
    "selftext": "\nIt\u2019s like going to a Casino and the owner tells you DO NOT PLAY THIS HAND YOU WILL LOSE YOUR MONEY. \n\nUnless they know you have 4 fucking ACES in your hand !\n\nEdit: we know they know we know that they can\u2019t win this time!",
    "title": "Why is MSM so concerned about MY MONEY and keeps telling me SELL SEL SELL?",
    "upvote_ratio": 0.98,
    "url": "https://www.reddit.com/r/GME/comments/mq12yj/why_is_msm_so_concerned_about_my_money_and_keeps/"
}