{
    "author": "shivr86",
    "created_utc": 1624975290.0,
    "distinguished": null,
    "edited": false,
    "id": "oa8vt4",
    "text_only": false,
    "flair_id": "24b09e66-85f9-11eb-b58c-0eb9c97053c1",
    "flair_text": "Meme \ud83e\udd23",
    "name": "t3_oa8vt4",
    "num_comments": 220,
    "permalink": "/r/Superstonk/comments/oa8vt4/this/",
    "score": 8853,
    "selftext": "",
    "title": "\ud83d\udc47\ud83c\udffd THIS.",
    "upvote_ratio": 0.97,
    "url": "https://i.redd.it/5bg1bhxao7871.jpg"
}