{
    "author": "mister_meseeks_1979",
    "created_utc": 1626402656.0,
    "distinguished": null,
    "edited": false,
    "id": "ol7nfa",
    "text_only": false,
    "flair_text": "Meme \ud83e\udd23",
    "name": "t3_ol7nfa",
    "num_comments": 11,
    "permalink": "/r/Superstonk/comments/ol7nfa/over_1mil_ftd_on_gme_from_1530_june/",
    "score": 195,
    "selftext": "",
    "title": "...over 1mil FTD on $GME from 15-30 June. \ud83d\ude02",
    "upvote_ratio": 0.89,
    "url": "https://i.redd.it/luwp0omlkhb71.jpg"
}