{
    "author": "Rainbowguy67",
    "created_utc": 1616698900.0,
    "distinguished": null,
    "edited": false,
    "id": "md5o04",
    "text_only": false,
    "flair_text": "DD",
    "name": "t3_md5o04",
    "num_comments": 762,
    "permalink": "/r/GME/comments/md5o04/ryan_cohen_just_tweeted_in_this_scene_ted_says/",
    "score": 13443,
    "selftext": "",
    "title": "Ryan Cohen just tweeted, in this scene Ted says: \u201cJesus this is weak, I\u2019m not even getting high\u201d 180$ is nothing\ud83d\ude80\ud83d\udc8e\ud83d\ude4c",
    "upvote_ratio": 0.98,
    "url": "https://i.redd.it/ogn4r76b28p61.jpg"
}