{
    "author": "Brooksee83",
    "created_utc": 1623939649.0,
    "distinguished": null,
    "edited": false,
    "id": "o1yeoi",
    "text_only": false,
    "flair_id": "57abfac2-85f9-11eb-a149-0e1c812e54f7",
    "flair_text": "Discussion \ud83e\udd8d",
    "name": "t3_o1yeoi",
    "num_comments": 310,
    "permalink": "/r/Superstonk/comments/o1yeoi/t212_just_sent_out_30day_notice_regarding_their/",
    "score": 908,
    "selftext": "",
    "title": "T212 just sent out 30day notice regarding their 'Share Lending Programme' and a Risk Warning. This bit caught my eye, and the timing seems sus...",
    "upvote_ratio": 0.98,
    "url": "https://www.reddit.com/gallery/o1yeoi"
}