{
    "author": "Stocks_7890_",
    "created_utc": 1623237007.0,
    "distinguished": null,
    "edited": false,
    "id": "nvt7hd",
    "text_only": false,
    "flair_text": "Question \u2753",
    "name": "t3_nvt7hd",
    "num_comments": 415,
    "permalink": "/r/Superstonk/comments/nvt7hd/can_i_get_a_dirty_hands_clean_money_flair_for_us/",
    "score": 3798,
    "selftext": "",
    "title": "Can I get a \"Dirty Hands, Clean Money\" flair for us blue-collar apes",
    "upvote_ratio": 0.93,
    "url": "https://i.redd.it/p5jhlmeh38471.jpg"
}