{
    "author": "bobsmith808",
    "created_utc": 1624046592.0,
    "distinguished": null,
    "edited": false,
    "id": "o2yxud",
    "text_only": false,
    "flair_id": "9dea31f0-9690-11eb-a861-0e3e97b993ff",
    "flair_text": "HODL \ud83d\udc8e\ud83d\ude4c",
    "name": "t3_o2yxud",
    "num_comments": 72,
    "permalink": "/r/Superstonk/comments/o2yxud/eod_1minute_candle_526k_doesnt_move_price_nothing/",
    "score": 794,
    "selftext": "",
    "title": "EOD 1minute candle @ 526k doesn't move price - Nothing to see here, move along.",
    "upvote_ratio": 0.85,
    "url": "https://i.redd.it/skpexj3ry2671.png"
}