{
    "author": "Grandpa_Lu",
    "created_utc": 1622446164.0,
    "distinguished": null,
    "edited": false,
    "id": "noxlj7",
    "text_only": false,
    "flair_text": "Discussion \ud83e\udd8d",
    "name": "t3_noxlj7",
    "num_comments": 53,
    "permalink": "/r/Superstonk/comments/noxlj7/if_i_remember_correctly_rgme_was_born_from/",
    "score": 0,
    "selftext": "",
    "title": "If I remember correctly r/gme was born from r/wallstreetbets and r/superstonk was born from r/gme. Which would make Superstonk exclusively GME (right?) but we tolerate the other stock?? Why come here? And why have they hijacked \"WE LIKE THE STOCK\" if that was Keith Gill's (NOT CRAMER'S) saying? \ud83e\udd14",
    "upvote_ratio": 0.45,
    "url": "https://i.redd.it/px7xuv0xre271.jpg"
}