{
    "author": "Bratlbart",
    "created_utc": 1624875405.0,
    "distinguished": null,
    "edited": false,
    "id": "o9hdne",
    "text_only": false,
    "flair_id": "24b09e66-85f9-11eb-b58c-0eb9c97053c1",
    "flair_text": "Meme \ud83e\udd23",
    "name": "t3_o9hdne",
    "num_comments": 38,
    "permalink": "/r/Superstonk/comments/o9hdne/what_they_say_vs_what_i_hear/",
    "score": 1915,
    "selftext": "",
    "title": "What they say vs. What I hear \ud83d\udc7e",
    "upvote_ratio": 0.94,
    "url": "https://i.redd.it/ry1oy2peez771.jpg"
}