{
    "author": "littlemisssniff",
    "created_utc": 1623784074.0,
    "distinguished": null,
    "edited": false,
    "id": "o0m0sn",
    "text_only": false,
    "flair_id": "a48b5c8e-8ff4-11eb-89b6-0e67f4f5fcb3",
    "flair_text": "News \ud83d\udcf0 | Media \ud83d\udcf1",
    "name": "t3_o0m0sn",
    "num_comments": 62,
    "permalink": "/r/Superstonk/comments/o0m0sn/big_short_investor_michael_burry_is_back_on/",
    "score": 597,
    "selftext": "",
    "title": "'Big Short' investor Michael Burry is back on Twitter - and warning of the biggest market bubble in history \ud83d\ude80",
    "upvote_ratio": 0.94,
    "url": "https://www.google.com/amp/s/www.businessinsider.com/big-short-michael-burry-twitter-return-biggest-market-bubble-ever-2021-6%3famp"
}