{
    "author": "JustBeingPunny",
    "created_utc": 1618756184.0,
    "distinguished": null,
    "edited": 1618760535.0,
    "id": "mtduwb",
    "text_only": true,
    "flair_id": "57abfac2-85f9-11eb-a149-0e1c812e54f7",
    "flair_text": "Discussion \ud83e\udd8d",
    "name": "t3_mtduwb",
    "num_comments": 93,
    "permalink": "/r/Superstonk/comments/mtduwb/the_ultimate_guide_for_retail/",
    "score": 2175,
    "selftext": "# MY DEAR APES.\n\n# Please follow the corresponding guide respective of your share quantity:\n\n&#x200B;\n\n* **X shares - Hodl until the millions.**\n\n&#x200B;\n\n* **XX shares - Hodl for the X shareholders.**\n\n&#x200B;\n\n* **XXX - Hodl for the X and XX shareholders.**\n\n&#x200B;\n\n* **XXXX - Hodl for everyone.** ***(You mini whales)***\n\n&#x200B;\n\n* **Exactly 200,000 shares - Do what ever you want, you earned this.**\n\n&#x200B;\n\n&#x200B;\n\nThe market has always prided itself on being every-man-for-himself. Apes? Apes make sure everyone gets their ticket's worth on the way to the moon. I don't need $100 million. I want 100 people to have $1 million.\n\n&#x200B;\n\n&#x200B;\n\n***HODL for the person who scraped enough to get just one share.***\n\n***HODL for the people who have been a victim of a broken, unjust financial system.***\n\n***HODL to show that the 99% are to be fucked with no more.***\n\n***HODL to ensure the financial inequality in the world is re-balanced.***\n\n***HODL to make the world a better place.***\n\n&#x200B;\n\n**Support a company. Like the stock.**\n\n**Can't stop. Won't stop. GameStop.**\n\n&#x200B;\n\n&#x200B;\n\n*Disclaimer- Do what ever you want. Don't base your financial investments on my past, current or future posts.*\n\n&#x200B;\n\nEdit - changed 'we' to '99%'. I didn't see a problem with it. Someone else did.",
    "title": "THE ULTIMATE GUIDE FOR RETAIL INVESTORS/SHAREHOLDERS WITH X,XX & XXX SHARES",
    "upvote_ratio": 0.97,
    "url": "https://www.reddit.com/r/Superstonk/comments/mtduwb/the_ultimate_guide_for_retail/"
}