{
    "author": "Zino82",
    "created_utc": 1624900531.0,
    "distinguished": null,
    "edited": false,
    "id": "o9ot9u",
    "text_only": false,
    "flair_id": "31ecc882-8cbd-11eb-877e-0e2a5e5fc207",
    "flair_text": "Fluff \u2601",
    "name": "t3_o9ot9u",
    "num_comments": 121,
    "permalink": "/r/Superstonk/comments/o9ot9u/by_saying_nothing_youve_said_all_i_needed_to_hear/",
    "score": 7759,
    "selftext": "",
    "title": "By saying nothing you've said all I needed to hear, Baird.",
    "upvote_ratio": 0.99,
    "url": "https://i.redd.it/b1c9pszsh1871.jpg"
}