{
    "author": "m3talrocksFPV",
    "created_utc": 1624888354.0,
    "distinguished": null,
    "edited": false,
    "id": "o9koxn",
    "text_only": false,
    "flair_id": "31ecc882-8cbd-11eb-877e-0e2a5e5fc207",
    "flair_text": "Fluff \u2601",
    "name": "t3_o9koxn",
    "num_comments": 245,
    "permalink": "/r/Superstonk/comments/o9koxn/gme_vs_spy_first_20_minutes_of_the_day/",
    "score": 5116,
    "selftext": "",
    "title": "Gme vs. SPY first 20 minutes of the day",
    "upvote_ratio": 0.98,
    "url": "https://i.redd.it/e7cviutsh0871.jpg"
}