{
    "author": "himinwin",
    "created_utc": 1625215481.0,
    "distinguished": null,
    "edited": false,
    "id": "oc61on",
    "text_only": false,
    "flair_id": "17e85f56-584b-11eb-a9a8-0e508049721d",
    "flair_text": "\u2601\ufe0f Fluff  \ud83c\udf4c",
    "name": "t3_oc61on",
    "num_comments": 173,
    "permalink": "/r/GME/comments/oc61on/there_must_be_an_announcement_coming_anybody_need/",
    "score": 4002,
    "selftext": "",
    "title": "\"There must be an announcement coming.\" Anybody need a lift?",
    "upvote_ratio": 0.97,
    "url": "https://i.redd.it/u10tukpahr871.gif"
}